{
 "created_at": "Tue Apr 16 02:59:37 +0000 2013",
 "id": 323994056185245696,
 "id_str": "323994056185245696",
 "full_text": "OMGGGG ...WHAAATTTT...???? RT @IthrustYunJae: OMGGGGG JPM CALLED ME JUST NOWWWWWWWW STILL TREMBLINGGGG OMGGG OMGGGGGG",
 "truncated": false,
 "display_text_range": [
  0,
  117
 ],
 "entities": {
  "hashtags": [],
  "symbols": [],
  "user_mentions": [],
  "urls": []
 },
 "source": "<a href=\"https://about.twitter.com/products/tweetdeck\" rel=\"nofollow\">TweetDeck</a>",
 "in_reply_to_status_id": null,
 "in_reply_to_status_id_str": null,
 "in_reply_to_user_id": null,
 "in_reply_to_user_id_str": null,
 "in_reply_to_screen_name": null,
 "user": {
  "id": 65408759,
  "id_str": "65408759",
  "name": "\u2665SyazzySalleh\u2665",
  "screen_name": "JaAz2615",
  "location": "\u2667  MyWorld  \u2667",
  "description": "\u2605 It's okay to believe yourself better than the rest of the planet, so long as you keep it to yourself.\u201d  \u2605 \u2661\u2570(*\u00b4\ufe36`*)\u256f\u2661",
  "url": null,
  "entities": {
   "description": {
    "urls": []
   }
  },
  "protected": false,
  "followers_count": 170,
  "friends_count": 296,
  "listed_count": 4,
  "created_at": "Thu Aug 13 16:56:45 +0000 2009",
  "favourites_count": 278,
  "utc_offset": null,
  "time_zone": null,
  "geo_enabled": true,
  "verified": false,
  "statuses_count": 32192,
  "lang": "en",
  "contributors_enabled": false,
  "is_translator": false,
  "is_translation_enabled": false,
  "profile_background_color": "FF6699",
  "profile_background_image_url": "http://abs.twimg.com/images/themes/theme1/bg.png",
  "profile_background_image_url_https": "https://abs.twimg.com/images/themes/theme1/bg.png",
  "profile_background_tile": true,
  "profile_image_url": "http://pbs.twimg.com/profile_images/1080092010214617088/SJ_n7wg8_normal.jpg",
  "profile_image_url_https": "https://pbs.twimg.com/profile_images/1080092010214617088/SJ_n7wg8_normal.jpg",
  "profile_banner_url": "https://pbs.twimg.com/profile_banners/65408759/1363610019",
  "profile_image_extensions_alt_text": null,
  "profile_banner_extensions_alt_text": null,
  "profile_link_color": "B40B43",
  "profile_sidebar_border_color": "FFFFFF",
  "profile_sidebar_fill_color": "EAF5BC",
  "profile_text_color": "362720",
  "profile_use_background_image": true,
  "has_extended_profile": false,
  "default_profile": false,
  "default_profile_image": false,
  "following": false,
  "follow_request_sent": false,
  "notifications": false,
  "translator_type": "none"
 },
 "geo": null,
 "coordinates": null,
 "place": null,
 "contributors": null,
 "is_quote_status": false,
 "retweet_count": 1,
 "favorite_count": 0,
 "favorited": false,
 "retweeted": false,
 "lang": "en"
}