{
 "created_at": "Mon Apr 15 20:32:29 +0000 2013",
 "id": 323896630678003712,
 "id_str": "323896630678003712",
 "full_text": "@e_hayes12 @murrayhead84 #Boston confirmed by whom? Nothing on live USA news channels",
 "truncated": false,
 "display_text_range": [
  0,
  85
 ],
 "entities": {
  "hashtags": [
   {
    "text": "Boston",
    "indices": [
     25,
     32
    ]
   }
  ],
  "symbols": [],
  "user_mentions": [
   {
    "screen_name": "e_hayes12",
    "name": "Elaine Hayes",
    "id": 21033615,
    "id_str": "21033615",
    "indices": [
     0,
     10
    ]
   },
   {
    "screen_name": "murrayhead84",
    "name": "John Murray",
    "id": 27961715,
    "id_str": "27961715",
    "indices": [
     11,
     24
    ]
   }
  ],
  "urls": []
 },
 "source": "<a href=\"http://blackberry.com/twitter\" rel=\"nofollow\">Twitter for BlackBerry\u00ae</a>",
 "in_reply_to_status_id": 323892897860685824,
 "in_reply_to_status_id_str": "323892897860685824",
 "in_reply_to_user_id": 21033615,
 "in_reply_to_user_id_str": "21033615",
 "in_reply_to_screen_name": "e_hayes12",
 "user": {
  "id": 49561645,
  "id_str": "49561645",
  "name": "David Ren\u00e9 Butcher",
  "screen_name": "davidbutcher007",
  "location": "Kilflynn Kerry Ireland",
  "description": "MSc. #photographer, #producer, #crowd #funder.     https://t.co/25eteqPGkA  When I grow up I want to be an engine driver",
  "url": "http://t.co/YMYxEdjpV3",
  "entities": {
   "url": {
    "urls": [
     {
      "url": "http://t.co/YMYxEdjpV3",
      "expanded_url": "http://www.imdb.me/davidrenebutcher",
      "display_url": "imdb.me/davidrenebutch\u2026",
      "indices": [
       0,
       22
      ]
     }
    ]
   },
   "description": {
    "urls": [
     {
      "url": "https://t.co/25eteqPGkA",
      "expanded_url": "https://www.facebook.com/davidrenebutcherindieprojects",
      "display_url": "facebook.com/davidrenebutch\u2026",
      "indices": [
       51,
       74
      ]
     }
    ]
   }
  },
  "protected": false,
  "followers_count": 241,
  "friends_count": 427,
  "listed_count": 30,
  "created_at": "Mon Jun 22 07:00:58 +0000 2009",
  "favourites_count": 11153,
  "utc_offset": null,
  "time_zone": null,
  "geo_enabled": false,
  "verified": false,
  "statuses_count": 13405,
  "lang": "en",
  "contributors_enabled": false,
  "is_translator": false,
  "is_translation_enabled": false,
  "profile_background_color": "642D8B",
  "profile_background_image_url": "http://abs.twimg.com/images/themes/theme10/bg.gif",
  "profile_background_image_url_https": "https://abs.twimg.com/images/themes/theme10/bg.gif",
  "profile_background_tile": false,
  "profile_image_url": "http://pbs.twimg.com/profile_images/2299274756/61be7994-58d1-40cd-9640-5d51f8c31d5a_normal.png",
  "profile_image_url_https": "https://pbs.twimg.com/profile_images/2299274756/61be7994-58d1-40cd-9640-5d51f8c31d5a_normal.png",
  "profile_banner_url": "https://pbs.twimg.com/profile_banners/49561645/1400754962",
  "profile_image_extensions_alt_text": null,
  "profile_banner_extensions_alt_text": null,
  "profile_link_color": "FF0000",
  "profile_sidebar_border_color": "65B0DA",
  "profile_sidebar_fill_color": "7AC3EE",
  "profile_text_color": "3D1957",
  "profile_use_background_image": true,
  "has_extended_profile": false,
  "default_profile": false,
  "default_profile_image": false,
  "following": false,
  "follow_request_sent": false,
  "notifications": false,
  "translator_type": "none"
 },
 "geo": null,
 "coordinates": null,
 "place": null,
 "contributors": null,
 "is_quote_status": false,
 "retweet_count": 0,
 "favorite_count": 0,
 "favorited": false,
 "retweeted": false,
 "lang": "en"
}